slim_id/__init__.py
slim_id/test.py
slim_id-0.1.1.dist-info/METADATA
slim_id-0.1.1.dist-info/WHEEL
slim_id-0.1.1.dist-info/entry_points.txt
slim_id-0.1.1.dist-info/top_level.txt
slim_id-0.1.1.dist-info/RECORD
